agntcy_acp/__init__.py
agntcy_acp/__main__.py
agntcy_acp/acp_v0/__init__.py
agntcy_acp/acp_v0/api_response.py
agntcy_acp/acp_v0/async_client/api/__init__.py
agntcy_acp/acp_v0/async_client/api/agents_api.py
agntcy_acp/acp_v0/async_client/api/stateless_runs_api.py
agntcy_acp/acp_v0/async_client/api/thread_runs_api.py
agntcy_acp/acp_v0/async_client/api/threads_api.py
agntcy_acp/acp_v0/async_client/api_client.py
agntcy_acp/acp_v0/async_client/rest.py
agntcy_acp/acp_v0/configuration.py
agntcy_acp/acp_v0/exceptions.py
agntcy_acp/acp_v0/models/__init__.py
agntcy_acp/acp_v0/models/agent.py
agntcy_acp/acp_v0/models/agent_acp_descriptor.py
agntcy_acp/acp_v0/models/agent_acp_spec.py
agntcy_acp/acp_v0/models/agent_acp_spec_interrupts_inner.py
agntcy_acp/acp_v0/models/agent_capabilities.py
agntcy_acp/acp_v0/models/agent_metadata.py
agntcy_acp/acp_v0/models/agent_ref.py
agntcy_acp/acp_v0/models/agent_search_request.py
agntcy_acp/acp_v0/models/config.py
agntcy_acp/acp_v0/models/content.py
agntcy_acp/acp_v0/models/content_one_of_inner.py
agntcy_acp/acp_v0/models/custom_run_result_update.py
agntcy_acp/acp_v0/models/message.py
agntcy_acp/acp_v0/models/message_any_block.py
agntcy_acp/acp_v0/models/message_text_block.py
agntcy_acp/acp_v0/models/run.py
agntcy_acp/acp_v0/models/run_create.py
agntcy_acp/acp_v0/models/run_create_stateful.py
agntcy_acp/acp_v0/models/run_create_stateless.py
agntcy_acp/acp_v0/models/run_error.py
agntcy_acp/acp_v0/models/run_interrupt.py
agntcy_acp/acp_v0/models/run_output.py
agntcy_acp/acp_v0/models/run_output_stream.py
agntcy_acp/acp_v0/models/run_result.py
agntcy_acp/acp_v0/models/run_search_request.py
agntcy_acp/acp_v0/models/run_stateful.py
agntcy_acp/acp_v0/models/run_stateless.py
agntcy_acp/acp_v0/models/run_status.py
agntcy_acp/acp_v0/models/run_wait_response_stateful.py
agntcy_acp/acp_v0/models/run_wait_response_stateless.py
agntcy_acp/acp_v0/models/stream_event_payload.py
agntcy_acp/acp_v0/models/stream_mode.py
agntcy_acp-1.5.2.dist-info/LICENSE
agntcy_acp-1.5.2.dist-info/METADATA
agntcy_acp-1.5.2.dist-info/WHEEL
agntcy_acp-1.5.2.dist-info/entry_points.txt
agntcy_acp-1.5.2.dist-info/RECORD
