Metadata-Version: 2.3
Name: agntcy-acp
Version: 1.5.2
Summary: Agent Connect Protocol SDK
License: Apache-2.0
Author: AGNTCY Internet of Agents Collective
Author-email: pypi@agntcy.io
Maintainer: AGNTCY Internet of Agents Collective
Maintainer-email: pypi@agntcy.io
Requires-Python: >=3.9.0, <4.0
Classifier: License :: OSI Approved :: Apache Software License
Classifier: Programming Language :: Python :: 3
Classifier: Programming Language :: Python :: 3.9
Classifier: Programming Language :: Python :: 3.10
Classifier: Programming Language :: Python :: 3.11
Classifier: Programming Language :: Python :: 3.12
Classifier: Programming Language :: Python :: 3.13
Provides-Extra: cli
Provides-Extra: iomapper-langgraph
Provides-Extra: langgraph
Requires-Dist: agntcy-iomapper[langgraph] (>=0.2.2) ; extra == "iomapper-langgraph"
Requires-Dist: aiofiles (>=24.1.0)
Requires-Dist: aiohttp (>=3.8.4)
Requires-Dist: aiohttp-retry (>=2.8.3)
Requires-Dist: click (>=8.1.8) ; extra == "cli"
Requires-Dist: datamodel-code-generator (>=0.25.6)
Requires-Dist: langgraph (>=0.3.16) ; extra == "langgraph"
Requires-Dist: openapi-spec-validator (>=0.7.1)
Requires-Dist: pydantic (>=2)
Requires-Dist: python-dateutil (>=2.8.2)
Requires-Dist: pyyaml (>=6.0.2)
Requires-Dist: typing-extensions (>=4.7.1)
Requires-Dist: urllib3 (>=1.25.3,<3.0.0)
Project-URL: Documentation, https://docs.agntcy.org/index.html
Project-URL: Homepage, https://github.com/agntcy/acp-sdk
Project-URL: Issues, https://github.com/agntcy/acp-sdk/issues
Project-URL: Source, https://github.com/agntcy/acp-sdk
